Metadata-Version: 1.0
Name: topinyin
Version: 0.5.5
Summary: translate chinese hanzi to pinyin by python
Home-page: https://github.com/yanwydxf/topinyin
Author: yanwydxf
Author-email: yanwydxf@163.com
License: UNKNOWN
Platform: UNKNOWN
